{
  "_class": "text",
  "attributedString": {
    "_class": "attributedString",
    "attributes": [
      {
        "_class": "stringAttribute",
        "attributes": {
          "MSAttributedStringColorAttribute": {
            "_class": "color",
            "alpha": 1,
            "blue": 1,
            "green": 1,
            "red": 1
          },
          "MSAttributedStringFontAttribute": {
            "_class": "fontDescriptor",
            "attributes": {
              "name": "SFProDisplay-Regular",
              "size": 16
            }
          },
          "kerning": 0,
          "paragraphStyle": {
            "_class": "paragraphStyle",
            "alignment": 2,
            "baseWritingDirection": 0,
            "maximumLineHeight": 24,
            "minimumLineHeight": 24
          },
          "strikethroughStyle": 0,
          "underlineStyle": 0
        },
        "length": 14,
        "location": 0
      }
    ],
    "string": "Primary button"
  },
  "automaticallyDrawOnUnderlyingPath": false,
  "booleanOperation": 0,
  "clippingMaskMode": 0,
  "do_objectID": "B68E9162-7701-44C4-A98C-F4CD2203EC67",
  "dontSynchroniseWithSymbol": false,
  "exportOptions": {
    "_class": "exportOptions",
    "do_objectID": "F3184E46-B072-4220-B3A3-C2EF12E98E33",
    "exportFormats": [
    ],
    "includedLayerIds": [
    ],
    "layerOptions": 0,
    "shouldTrim": false
  },
  "frame": {
    "_class": "rect",
    "constrainProportions": false,
    "do_objectID": "2B27DAEB-8431-495E-985C-7CF56CB09567",
    "height": 24,
    "width": 165,
    "x": 0,
    "y": 11
  },
  "glyphBounds": "{{34, 6}, {97, 16}}",
  "hasClippingMask": false,
  "isFixedToViewport": false,
  "isFlippedHorizontal": false,
  "isFlippedVertical": false,
  "isLocked": false,
  "isVisible": true,
  "layerListExpandedType": 0,
  "lineSpacingBehaviour": 2,
  "name": "Button text",
  "nameIsFixed": true,
  "resizingConstraint": 59,
  "resizingType": 0,
  "rotation": 0,
  "sharedStyleID": "B295793B-9354-491A-A4F5-BFFF477DD12F",
  "shouldBreakMaskChain": false,
  "style": {
    "_class": "style",
    "do_objectID": "E8BBB84B-0042-4EEB-B3D4-B6F835DF07B2",
    "endMarkerType": 0,
    "miterLimit": 10,
    "startMarkerType": 0,
    "textStyle": {
      "_class": "textStyle",
      "encodedAttributes": {
        "MSAttributedStringColorAttribute": {
          "_class": "color",
          "alpha": 1,
          "blue": 1,
          "green": 1,
          "red": 1
        },
        "MSAttributedStringFontAttribute": {
          "_class": "fontDescriptor",
          "attributes": {
            "name": "SFProDisplay-Regular",
            "size": 16
          }
        },
        "kerning": 0,
        "paragraphStyle": {
          "_class": "paragraphStyle",
          "alignment": 2,
          "baseWritingDirection": 0,
          "maximumLineHeight": 24,
          "minimumLineHeight": 24
        },
        "strikethroughStyle": 0,
        "underlineStyle": 0
      },
      "verticalAlignment": 0
    },
    "windingRule": 1
  },
  "textBehaviour": 1
}