{
  "_class": "group",
  "booleanOperation": 0,
  "clippingMaskMode": 0,
  "do_objectID": "B8ED9881-A635-4DE7-88F2-3840D16235F0",
  "exportOptions": {
    "_class": "exportOptions",
    "do_objectID": "ABBFA89F-0111-4C77-9290-ECE7CD5E2071",
    "exportFormats": [
    ],
    "includedLayerIds": [
    ],
    "layerOptions": 0,
    "shouldTrim": false
  },
  "frame": {
    "_class": "rect",
    "constrainProportions": false,
    "do_objectID": "028AA1E8-7963-49FB-86E1-693E72154442",
    "height": 171,
    "width": 320,
    "x": 0,
    "y": 0
  },
  "groupLayout": {
    "_class": "MSImmutableFreeformGroupLayout"
  },
  "hasClickThrough": false,
  "hasClippingMask": false,
  "isFixedToViewport": false,
  "isFlippedHorizontal": false,
  "isFlippedVertical": false,
  "isLocked": false,
  "isVisible": true,
  "layerListExpandedType": 0,
  "layers": [
    {
      "class": "rectangle",
      "id": "F3CF5783-B4E8-45A2-8DE5-3FADB6610189"
    },
    {
      "class": "rectangle",
      "id": "7519453F-667A-4AD0-956D-C52822AE459C"
    }
  ],
  "name": "padding",
  "nameIsFixed": true,
  "resizingConstraint": 63,
  "resizingType": 0,
  "rotation": 0,
  "shouldBreakMaskChain": false,
  "style": {
    "_class": "style",
    "do_objectID": "C6EFA0E5-AD57-43DF-8365-FAE8256F95D3",
    "endMarkerType": 0,
    "miterLimit": 10,
    "startMarkerType": 0,
    "windingRule": 1
  }
}