{
  "_class": "symbolInstance",
  "booleanOperation": 0,
  "clippingMaskMode": 0,
  "do_objectID": "9A91D58E-B85D-4EB5-8E57-7B19A537FBDD",
  "exportOptions": {
    "_class": "exportOptions",
    "do_objectID": "134E0246-CBE0-4B93-9A52-345A7D8927F5",
    "exportFormats": [
    ],
    "includedLayerIds": [
    ],
    "layerOptions": 0,
    "shouldTrim": false
  },
  "frame": {
    "_class": "rect",
    "constrainProportions": true,
    "do_objectID": "2A861F4B-783D-4908-B1D1-DDDCCBAB544B",
    "height": 47,
    "width": 192,
    "x": 0,
    "y": 24
  },
  "hasClippingMask": false,
  "horizontalSpacing": 0,
  "isFixedToViewport": false,
  "isFlippedHorizontal": false,
  "isFlippedVertical": false,
  "isLocked": false,
  "isVisible": true,
  "layerListExpandedType": 0,
  "name": "logo / coa-black",
  "nameIsFixed": false,
  "overrideValues": [
  ],
  "resizingConstraint": 9,
  "resizingType": 0,
  "rotation": 0,
  "scale": 1,
  "shouldBreakMaskChain": false,
  "style": {
    "_class": "style",
    "do_objectID": "4F2E9D42-394B-4EB3-AFD7-753A00E39850",
    "endMarkerType": 0,
    "miterLimit": 10,
    "startMarkerType": 0,
    "windingRule": 1
  },
  "symbolID": "50F0BC2C-B124-4ABA-BF8B-EBD92CCE41CB",
  "verticalSpacing": 0
}