{
  "_class": "symbolInstance",
  "booleanOperation": 0,
  "clippingMaskMode": 0,
  "do_objectID": "CE4D21D2-7346-480D-A1A7-0DB00003C41D",
  "exportOptions": {
    "_class": "exportOptions",
    "do_objectID": "0D809A32-B122-41CA-A82E-5D9D9ECEE862",
    "exportFormats": [
    ],
    "includedLayerIds": [
    ],
    "layerOptions": 0,
    "shouldTrim": false
  },
  "frame": {
    "_class": "rect",
    "constrainProportions": false,
    "do_objectID": "5B307F71-FF85-486E-8D16-6424EF5F9865",
    "height": 42,
    "width": 174,
    "x": 27,
    "y": 194
  },
  "hasClippingMask": false,
  "horizontalSpacing": 0,
  "isFixedToViewport": false,
  "isFlippedHorizontal": false,
  "isFlippedVertical": false,
  "isLocked": false,
  "isVisible": true,
  "layerListExpandedType": 0,
  "name": "Radio Button / light / enabled checked",
  "nameIsFixed": false,
  "overrideValues": [
  ],
  "resizingConstraint": 63,
  "resizingType": 0,
  "rotation": 0,
  "scale": 1,
  "shouldBreakMaskChain": false,
  "style": {
    "_class": "style",
    "do_objectID": "0E6442FB-A275-498D-A02C-50ED6990CBC7",
    "endMarkerType": 0,
    "miterLimit": 10,
    "startMarkerType": 0,
    "windingRule": 1
  },
  "symbolID": "32F78C37-77B6-45C8-A297-556CF13C3564",
  "verticalSpacing": 0
}