{
  "_class": "symbolInstance",
  "booleanOperation": 0,
  "clippingMaskMode": 0,
  "do_objectID": "D779D3ED-C871-4A15-B373-AD3F3BA9D1D2",
  "exportOptions": {
    "_class": "exportOptions",
    "do_objectID": "CCE6FABE-BC5B-45BA-A837-C446936CEDE3",
    "exportFormats": [
    ],
    "includedLayerIds": [
    ],
    "layerOptions": 0,
    "shouldTrim": false
  },
  "frame": {
    "_class": "rect",
    "constrainProportions": false,
    "do_objectID": "9C79AD67-17CE-4A65-9576-5DBBC5DB6914",
    "height": 64,
    "width": 71,
    "x": 536,
    "y": 204
  },
  "hasClippingMask": false,
  "horizontalSpacing": 0,
  "isFixedToViewport": false,
  "isFlippedHorizontal": false,
  "isFlippedVertical": false,
  "isLocked": false,
  "isVisible": true,
  "layerListExpandedType": 0,
  "name": "main-nav / light / desktop item active copy 3",
  "nameIsFixed": false,
  "overrideValues": [
    {
      "_class": "overrideValue",
      "do_objectID": "19529320-C9A0-4877-BBEE-66DCFAF80AA7",
      "overrideName": "A14D5527-7DAD-4C60-99E3-E6772264B9F3_stringValue",
      "value": "News"
    }
  ],
  "resizingConstraint": 63,
  "resizingType": 0,
  "rotation": 0,
  "scale": 1,
  "shouldBreakMaskChain": false,
  "style": {
    "_class": "style",
    "do_objectID": "E283E235-B269-473E-B881-0398BD6515AA",
    "endMarkerType": 0,
    "miterLimit": 10,
    "startMarkerType": 0,
    "windingRule": 1
  },
  "symbolID": "DFE49F20-CADD-447E-BB25-8A5151D3CA3F",
  "verticalSpacing": 0
}